esprit/__init__.py
esprit/absence.py
esprit/auth.py
esprit/credit.py
esprit/esprit.py
esprit/grade.py
esprit/time_schedule.py
esprit/utils.py
esprit_py-0.5.1.dist-info/LICENSE
esprit_py-0.5.1.dist-info/METADATA
esprit_py-0.5.1.dist-info/WHEEL
esprit_py-0.5.1.dist-info/top_level.txt
esprit_py-0.5.1.dist-info/RECORD
