Metadata-Version: 2.1
Name: esprit-py
Version: 0.5.1
Summary: A fast, lightweight Python library for interacting with data from esprit-tn.com
Home-page: https://github.com/TheLime1/esprit.py
Author: Lime1 (Aymen Hmani)
Keywords: python,api
Classifier: Development Status :: 4 - Beta
Classifier: Intended Audience :: Developers
Classifier: Programming Language :: Python :: 3
Classifier: Operating System :: Unix
Classifier: Operating System :: MacOS :: MacOS X
Classifier: Operating System :: Microsoft :: Windows
Classifier: License :: OSI Approved :: MIT License
License-File: LICENSE
Requires-Dist: requests
Requires-Dist: beautifulsoup4
Requires-Dist: PyPDF2
Requires-Dist: numpy
Requires-Dist: pandas
